DDRLtestV0/__init__.py
DDRLtestV0/onpolicyalgorithm.py
DDRLtestV0/ppo.py
DDRLtestV0/train.py
ddrltestv0-1.0.1.dist-info/METADATA
ddrltestv0-1.0.1.dist-info/WHEEL
ddrltestv0-1.0.1.dist-info/licenses/LICENSE
ddrltestv0-1.0.1.dist-info/licenses/LICENSE.txt
ddrltestv0-1.0.1.dist-info/RECORD
