Metadata-Version: 2.4
Name: DDRLtestV0
Version: 1.0.1
Summary: ADB操作包
Project-URL: Homepage, http://xxx.xxx.xxx
Author: yuchen liang
License: Copyright (c) 2018 The Python Packaging Authority
License-File: LICENSE
License-File: LICENSE.txt
Classifier: License :: OSI Approved :: MIT License
Classifier: Operating System :: OS Independent
Classifier: Programming Language :: Python :: 3
Requires-Python: >=3.8
Requires-Dist: gymnasium==1.0.0
Requires-Dist: stable-baselines3==2.4.0
